[
  {
    "iteration": 0,
    "n_initial_points": 3,
    "q": 3,
    "m": 10,
    "target": "Query26",
    "suggested_minimum": [
      4.846218190861347,
      2.8341087187223764
    ],
    "known_minimum": [
      3.0,
      9.0
    ],
    "closest_point_in_domain": [
      5.0,
      4.0
    ],
    "computed_cost": 1300404.5,
    "n_evaluations": 6,
    "error": 589994.9,
    "error_ratio": 0.8304996159961803
  },
  {
    "iteration": 1,
    "n_initial_points": 3,
    "q": 3,
    "m": 10,
    "target": "Query26",
    "suggested_minimum": [
      5.444231087314445,
      2.7913551207651293
    ],
    "known_minimum": [
      3.0,
      9.0
    ],
    "closest_point_in_domain": [
      5.0,
      4.0
    ],
    "computed_cost": 1300404.5,
    "n_evaluations": 9,
    "error": 589994.9,
    "error_ratio": 0.8304996159961803
  },
  {
    "iteration": 2,
    "n_initial_points": 3,
    "q": 3,
    "m": 10,
    "target": "Query26",
    "suggested_minimum": [
      5.400533024886187,
      2.8015415692681436
    ],
    "known_minimum": [
      3.0,
      9.0
    ],
    "closest_point_in_domain": [
      5.0,
      4.0
    ],
    "computed_cost": 1300404.5,
    "n_evaluations": 12,
    "error": 589994.9,
    "error_ratio": 0.8304996159961803
  },
  {
    "iteration": 3,
    "n_initial_points": 3,
    "q": 3,
    "m": 10,
    "target": "Query26",
    "suggested_minimum": [
      5.395978287667204,
      2.7917708903998215
    ],
    "known_minimum": [
      3.0,
      9.0
    ],
    "closest_point_in_domain": [
      5.0,
      4.0
    ],
    "computed_cost": 1300404.5,
    "n_evaluations": 15,
    "error": 589994.9,
    "error_ratio": 0.8304996159961803
  },
  {
    "iteration": 4,
    "n_initial_points": 3,
    "q": 3,
    "m": 10,
    "target": "Query26",
    "suggested_minimum": [
      5.344275968785519,
      2.7788090457777694
    ],
    "known_minimum": [
      3.0,
      9.0
    ],
    "closest_point_in_domain": [
      5.0,
      4.0
    ],
    "computed_cost": 1300404.5,
    "n_evaluations": 18,
    "error": 589994.9,
    "error_ratio": 0.8304996159961803
  }
]