[
  {
    "iteration": 0,
    "n_initial_points": 7,
    "q": 3,
    "m": 12,
    "target": "StereoMatch",
    "suggested_minimum": [
      49.200789758498395,
      2.1399994805459386,
      14.007116017253956,
      8.765048787165261
    ],
    "known_minimum": [
      14,
      3,
      1,
      1
    ],
    "closest_point_in_domain": [
      54,
      2,
      14,
      9
    ],
    "computed_cost": 108819.0,
    "n_evaluations": 10,
    "error": 72028.0,
    "error_ratio": 1.9577614090402544
  },
  {
    "iteration": 1,
    "n_initial_points": 7,
    "q": 3,
    "m": 12,
    "target": "StereoMatch",
    "suggested_minimum": [
      49.013430664648816,
      2.213837236197983,
      13.983696796566885,
      8.9687091997509
    ],
    "known_minimum": [
      14,
      3,
      1,
      1
    ],
    "closest_point_in_domain": [
      54,
      2,
      14,
      9
    ],
    "computed_cost": 108819.0,
    "n_evaluations": 13,
    "error": 72028.0,
    "error_ratio": 1.9577614090402544
  },
  {
    "iteration": 2,
    "n_initial_points": 7,
    "q": 3,
    "m": 12,
    "target": "StereoMatch",
    "suggested_minimum": [
      63.72487197618069,
      2.5707916938742104,
      6.695127353340838,
      7.93194363652029
    ],
    "known_minimum": [
      14,
      3,
      1,
      1
    ],
    "closest_point_in_domain": [
      64,
      3,
      7,
      8
    ],
    "computed_cost": 76120.0,
    "n_evaluations": 16,
    "error": 39329.0,
    "error_ratio": 1.068984262455492
  },
  {
    "iteration": 3,
    "n_initial_points": 7,
    "q": 3,
    "m": 12,
    "target": "StereoMatch",
    "suggested_minimum": [
      60.39563368489179,
      2.6263733040074206,
      7.2377908503192945,
      8.763561699561434
    ],
    "known_minimum": [
      14,
      3,
      1,
      1
    ],
    "closest_point_in_domain": [
      64,
      3,
      7,
      9
    ],
    "computed_cost": 69066.0,
    "n_evaluations": 19,
    "error": 32275.0,
    "error_ratio": 0.8772525889483841
  },
  {
    "iteration": 4,
    "n_initial_points": 7,
    "q": 3,
    "m": 12,
    "target": "StereoMatch",
    "suggested_minimum": [
      60.80247017846403,
      2.6941084929938985,
      7.71566616947733,
      8.668729060383678
    ],
    "known_minimum": [
      14,
      3,
      1,
      1
    ],
    "closest_point_in_domain": [
      64,
      3,
      8,
      9
    ],
    "computed_cost": 89217.0,
    "n_evaluations": 22,
    "error": 52426.0,
    "error_ratio": 1.4249680628414558
  },
  {
    "iteration": 5,
    "n_initial_points": 7,
    "q": 3,
    "m": 12,
    "target": "StereoMatch",
    "suggested_minimum": [
      33.18271797888027,
      2.6622362711245358,
      4.7555284204681,
      6.113209824282604
    ],
    "known_minimum": [
      14,
      3,
      1,
      1
    ],
    "closest_point_in_domain": [
      34,
      3,
      5,
      6
    ],
    "computed_cost": 60192.0,
    "n_evaluations": 25,
    "error": 23401.0,
    "error_ratio": 0.6360522953983311
  },
  {
    "iteration": 6,
    "n_initial_points": 7,
    "q": 3,
    "m": 12,
    "target": "StereoMatch",
    "suggested_minimum": [
      34.50026274891906,
      2.7999689800016347,
      4.509027947973246,
      6.327916112769193
    ],
    "known_minimum": [
      14,
      3,
      1,
      1
    ],
    "closest_point_in_domain": [
      34,
      3,
      5,
      6
    ],
    "computed_cost": 56466.0,
    "n_evaluations": 28,
    "error": 19675.0,
    "error_ratio": 0.5347775271126091
  },
  {
    "iteration": 7,
    "n_initial_points": 7,
    "q": 3,
    "m": 12,
    "target": "StereoMatch",
    "suggested_minimum": [
      32.55385729690676,
      2.877770612034886,
      4.20335677678267,
      6.351885943406454
    ],
    "known_minimum": [
      14,
      3,
      1,
      1
    ],
    "closest_point_in_domain": [
      34,
      3,
      4,
      6
    ],
    "computed_cost": 54312.0,
    "n_evaluations": 31,
    "error": 17521.0,
    "error_ratio": 0.4762305998749694
  },
  {
    "iteration": 8,
    "n_initial_points": 7,
    "q": 3,
    "m": 12,
    "target": "StereoMatch",
    "suggested_minimum": [
      32.360541737886514,
      2.9999999999999925,
      3.716282190539949,
      6.037549049818652
    ],
    "known_minimum": [
      14,
      3,
      1,
      1
    ],
    "closest_point_in_domain": [
      34,
      3,
      4,
      6
    ],
    "computed_cost": 54312.0,
    "n_evaluations": 34,
    "error": 17521.0,
    "error_ratio": 0.4762305998749694
  },
  {
    "iteration": 9,
    "n_initial_points": 7,
    "q": 3,
    "m": 12,
    "target": "StereoMatch",
    "suggested_minimum": [
      34.88506714001566,
      3.0,
      1.078092332706935,
      2.7005538298433733
    ],
    "known_minimum": [
      14,
      3,
      1,
      1
    ],
    "closest_point_in_domain": [
      34,
      3,
      1,
      3
    ],
    "computed_cost": 40638.0,
    "n_evaluations": 37,
    "error": 3847.0,
    "error_ratio": 0.10456361610176401
  }
]