[{"iteration": 1, "n_initial_points": 5, "target": "Stereomatch", "suggested_minimum": [54.0, 3.0, 3.0, 2.0], "known_minimum": [14, 3, 1, 1], "closest_point_in_domain": [54.0, 3.0, 3.0, 2.0], "computed_cost": 43390.0, "n_evaluations": 6, "error": 6599.0, "error_ratio": 0.1793645184963714, "algorithm": "EI (memqueue 0)"}, {"iteration": 2, "n_initial_points": 5, "target": "Stereomatch", "suggested_minimum": [64.0, 3.0, 5.0, 2.0], "known_minimum": [14, 3, 1, 1], "closest_point_in_domain": [64.0, 3.0, 5.0, 2.0], "computed_cost": 47466.0, "n_evaluations": 7, "error": 10675.0, "error_ratio": 0.2901524829441983, "algorithm": "EI (memqueue 0)"}, {"iteration": 3, "n_initial_points": 5, "target": "Stereomatch", "suggested_minimum": [54.0, 3.0, 1.0, 1.0], "known_minimum": [14, 3, 1, 1], "closest_point_in_domain": [54.0, 3.0, 1.0, 1.0], "computed_cost": 36900.0, "n_evaluations": 8, "error": 109.0, "error_ratio": 0.002962681090484086, "algorithm": "EI (memqueue 0)"}, {"iteration": 4, "n_initial_points": 5, "target": "Stereomatch", "suggested_minimum": [14.0, 2.0, 9.0, 11.0], "known_minimum": [14, 3, 1, 1], "closest_point_in_domain": [14.0, 2.0, 9.0, 11.0], "computed_cost": 113729.0, "n_evaluations": 9, "error": 76938.0, "error_ratio": 2.091217960914354, "algorithm": "EI (memqueue 0)"}, {"iteration": 5, "n_initial_points": 5, "target": "Stereomatch", "suggested_minimum": [54.0, 3.0, 2.0, 2.0], "known_minimum": [14, 3, 1, 1], "closest_point_in_domain": [54.0, 3.0, 2.0, 2.0], "computed_cost": 41296.0, "n_evaluations": 10, "error": 4505.0, "error_ratio": 0.12244842488652116, "algorithm": "EI (memqueue 0)"}, {"iteration": 6, "n_initial_points": 5, "target": "Stereomatch", "suggested_minimum": [14.0, 3.0, 10.0, 10.0], "known_minimum": [14, 3, 1, 1], "closest_point_in_domain": [14.0, 3.0, 10.0, 10.0], "computed_cost": 84800.0, "n_evaluations": 11, "error": 48009.0, "error_ratio": 1.3049115272756924, "algorithm": "EI (memqueue 0)"}, {"iteration": 7, "n_initial_points": 5, "target": "Stereomatch", "suggested_minimum": [24.0, 3.0, 1.0, 1.0], "known_minimum": [14, 3, 1, 1], "closest_point_in_domain": [24.0, 3.0, 1.0, 1.0], "computed_cost": 37785.0, "n_evaluations": 12, "error": 994.0, "error_ratio": 0.02701747710037781, "algorithm": "EI (memqueue 0)"}, {"iteration": 8, "n_initial_points": 5, "target": "Stereomatch", "suggested_minimum": [34.0, 3.0, 1.0, 1.0], "known_minimum": [14, 3, 1, 1], "closest_point_in_domain": [34.0, 3.0, 1.0, 1.0], "computed_cost": 37887.0, "n_evaluations": 13, "error": 1096.0, "error_ratio": 0.0297898942676198, "algorithm": "EI (memqueue 0)"}, {"iteration": 9, "n_initial_points": 5, "target": "Stereomatch", "suggested_minimum": [24.0, 3.0, 1.0, 1.0], "known_minimum": [14, 3, 1, 1], "closest_point_in_domain": [24.0, 3.0, 1.0, 1.0], "computed_cost": 37785.0, "n_evaluations": 14, "error": 994.0, "error_ratio": 0.02701747710037781, "algorithm": "EI (memqueue 0)"}, {"iteration": 10, "n_initial_points": 5, "target": "Stereomatch", "suggested_minimum": [64.0, 3.0, 1.0, 1.0], "known_minimum": [14, 3, 1, 1], "closest_point_in_domain": [64.0, 3.0, 1.0, 1.0], "computed_cost": 37218.0, "n_evaluations": 15, "error": 427.0, "error_ratio": 0.011606099317767932, "algorithm": "EI (memqueue 0)"}, {"iteration": 11, "n_initial_points": 5, "target": "Stereomatch", "suggested_minimum": [34.0, 3.0, 1.0, 1.0], "known_minimum": [14, 3, 1, 1], "closest_point_in_domain": [34.0, 3.0, 1.0, 1.0], "computed_cost": 37887.0, "n_evaluations": 16, "error": 1096.0, "error_ratio": 0.0297898942676198, "algorithm": "EI (memqueue 0)"}, {"iteration": 12, "n_initial_points": 5, "target": "Stereomatch", "suggested_minimum": [64.0, 3.0, 6.0, 12.0], "known_minimum": [14, 3, 1, 1], "closest_point_in_domain": [64.0, 3.0, 6.0, 12.0], "computed_cost": 83988.0, "n_evaluations": 17, "error": 47197.0, "error_ratio": 1.2828409121796092, "algorithm": "EI (memqueue 0)"}, {"iteration": 13, "n_initial_points": 5, "target": "Stereomatch", "suggested_minimum": [14.0, 3.0, 1.0, 1.0], "known_minimum": [14, 3, 1, 1], "closest_point_in_domain": [14.0, 3.0, 1.0, 1.0], "computed_cost": 36791.0, "n_evaluations": 18, "error": 0.0, "error_ratio": 0.0, "algorithm": "EI (memqueue 0)"}]